poetry_plugin_migrate/__init__.py
poetry_plugin_migrate/command.py
poetry_plugin_migrate/migrator.py
poetry_plugin_migrate/plugin.py
poetry_plugin_migrate-0.1.1.dist-info/LICENSE
poetry_plugin_migrate-0.1.1.dist-info/METADATA
poetry_plugin_migrate-0.1.1.dist-info/WHEEL
poetry_plugin_migrate-0.1.1.dist-info/entry_points.txt
poetry_plugin_migrate-0.1.1.dist-info/RECORD
