Metadata-Version: 2.3
Name: poetry-plugin-migrate
Version: 0.1.1
Summary: Poetry plugin to migrate pyproject.toml from Poetry v1 to v2 (PEP-621 compliant)
License: MIT
Keywords: poetry,migrate,PEP-621,pyproject.toml
Author: zyf722
Author-email: MaxMixAlex@protonmail.com
Requires-Python: >=3.9,<4.0
Classifier: Development Status :: 4 - Beta
Classifier: Intended Audience :: Developers
Classifier: License :: OSI Approved :: MIT License
Classifier: Operating System :: OS Independent
Classifier: Programming Language :: Python :: 3
Classifier: Programming Language :: Python :: 3.9
Classifier: Programming Language :: Python :: 3.10
Classifier: Programming Language :: Python :: 3.11
Classifier: Programming Language :: Python :: 3.12
Classifier: Programming Language :: Python :: 3.13
Requires-Dist: poetry (>=2.0.0,<3.0.0)
Project-URL: Homepage, https://github.com/zyf722/poetry-plugin-migrate
Project-URL: Repository, https://github.com/zyf722/poetry-plugin-migrate
